{
  "$schema_note": "Rojo project — once you 'rojo init' from diablow.rbxl this maps services to disk. STUB — needs full extraction before CI works.",
  "name": "diablow",
  "tree": {
    "$className": "DataModel",
    "ReplicatedStorage": {
      "$path": "src/ReplicatedStorage"
    },
    "ServerScriptService": {
      "$path": "src/ServerScriptService"
    },
    "ServerStorage": {
      "$path": "src/ServerStorage"
    },
    "StarterPlayer": {
      "$path": "src/StarterPlayer"
    },
    "Workspace": {
      "$properties": {
        "FilteringEnabled": true
      }
    }
  }
}
